data_tutorials/__init__.py
data_tutorials/data.py
data_tutorials-0.3.3.dist-info/licenses/LICENSE
data_tutorials-0.3.3.dist-info/METADATA
data_tutorials-0.3.3.dist-info/WHEEL
data_tutorials-0.3.3.dist-info/top_level.txt
data_tutorials-0.3.3.dist-info/RECORD
