Metadata-Version: 2.4
Name: data-tutorials
Version: 0.3.3
Summary: download data for tutorials
Author-email: Alin M Elena <alin@elena.re>
Maintainer-email: Alin M Elena <alin@elena.re>
License: MIT License
Project-URL: Homepage, https://github.com/ddmms/data-tutorials
Project-URL: Repository, https://github.com/ddmms/data-tutorials.git
Project-URL: Issues, https://github.com/ddmms/data-tutorials/issues
Keywords: data,download
Classifier: Development Status :: 4 - Beta
Classifier: Programming Language :: Python :: 3
Classifier: License :: OSI Approved :: MIT License
Classifier: Operating System :: OS Independent
Requires-Python: >=3.9
License-File: LICENSE
Requires-Dist: pytest
Requires-Dist: ruff
Requires-Dist: tqdm
Dynamic: license-file
